setup.cfg
setup.py
admin_extend/__init__.py
admin_extend/extend.py
django_admin_extend.egg-info/PKG-INFO
django_admin_extend.egg-info/SOURCES.txt
django_admin_extend.egg-info/dependency_links.txt
django_admin_extend.egg-info/requires.txt
django_admin_extend.egg-info/top_level.txt