Metadata-Version: 1.1
Name: django-admin-extend
Version: 0.0.3
Summary: Provides functionality for extendingModelAdmin classes that have alreadybeen registered by other apps
Home-page: https://github.com/kux/django-admin-extend
Author: Ioan Alexandru Cucu
Author-email: alexandruioan.cucu@gmail.com
License: UNKNOWN
Download-URL: https://github.com/kux/django-admin-extend/archive/0.0.3.tar.gz
Platform: UNKNOWN
